graphlime/__init__.py
graphlime/explainers.py
graphlime-0.1.1.dist-info/LICENSE
graphlime-0.1.1.dist-info/METADATA
graphlime-0.1.1.dist-info/WHEEL
graphlime-0.1.1.dist-info/top_level.txt
graphlime-0.1.1.dist-info/RECORD
