Metadata-Version: 2.1
Name: graphlime
Version: 0.1.1
Summary: A package
Home-page: https://github.com/WilliamCCHuang/GraphLIME
Author: williamcchuang
Author-email: hang6318179@gmail.com
License: UNKNOWN
Platform: UNKNOWN
Classifier: Programming Language :: Python :: 3
Classifier: License :: OSI Approved :: MIT License
Classifier: Operating System :: OS Independent
Requires-Python: >=3.6
